Xlib-stubs/METADATA.toml
Xlib-stubs/X.pyi
Xlib-stubs/XK.pyi
Xlib-stubs/Xatom.pyi
Xlib-stubs/Xcursorfont.pyi
Xlib-stubs/Xutil.pyi
Xlib-stubs/__init__.pyi
Xlib-stubs/_typing.pyi
Xlib-stubs/display.pyi
Xlib-stubs/error.pyi
Xlib-stubs/py.typed
Xlib-stubs/rdb.pyi
Xlib-stubs/threaded.pyi
Xlib-stubs/xauth.pyi
Xlib-stubs/ext/__init__.pyi
Xlib-stubs/ext/composite.pyi
Xlib-stubs/ext/damage.pyi
Xlib-stubs/ext/dpms.pyi
Xlib-stubs/ext/ge.pyi
Xlib-stubs/ext/nvcontrol.pyi
Xlib-stubs/ext/randr.pyi
Xlib-stubs/ext/record.pyi
Xlib-stubs/ext/res.pyi
Xlib-stubs/ext/screensaver.pyi
Xlib-stubs/ext/security.pyi
Xlib-stubs/ext/shape.pyi
Xlib-stubs/ext/xfixes.pyi
Xlib-stubs/ext/xinerama.pyi
Xlib-stubs/ext/xinput.pyi
Xlib-stubs/ext/xtest.pyi
Xlib-stubs/keysymdef/__init__.pyi
Xlib-stubs/keysymdef/apl.pyi
Xlib-stubs/keysymdef/arabic.pyi
Xlib-stubs/keysymdef/cyrillic.pyi
Xlib-stubs/keysymdef/greek.pyi
Xlib-stubs/keysymdef/hebrew.pyi
Xlib-stubs/keysymdef/katakana.pyi
Xlib-stubs/keysymdef/korean.pyi
Xlib-stubs/keysymdef/latin1.pyi
Xlib-stubs/keysymdef/latin2.pyi
Xlib-stubs/keysymdef/latin3.pyi
Xlib-stubs/keysymdef/latin4.pyi
Xlib-stubs/keysymdef/miscellany.pyi
Xlib-stubs/keysymdef/publishing.pyi
Xlib-stubs/keysymdef/special.pyi
Xlib-stubs/keysymdef/technical.pyi
Xlib-stubs/keysymdef/thai.pyi
Xlib-stubs/keysymdef/xf86.pyi
Xlib-stubs/keysymdef/xk3270.pyi
Xlib-stubs/keysymdef/xkb.pyi
Xlib-stubs/protocol/__init__.pyi
Xlib-stubs/protocol/display.pyi
Xlib-stubs/protocol/event.pyi
Xlib-stubs/protocol/request.pyi
Xlib-stubs/protocol/rq.pyi
Xlib-stubs/protocol/structs.pyi
Xlib-stubs/support/__init__.pyi
Xlib-stubs/support/connect.pyi
Xlib-stubs/support/lock.pyi
Xlib-stubs/support/unix_connect.pyi
Xlib-stubs/support/vms_connect.pyi
Xlib-stubs/xobject/__init__.pyi
Xlib-stubs/xobject/colormap.pyi
Xlib-stubs/xobject/cursor.pyi
Xlib-stubs/xobject/drawable.pyi
Xlib-stubs/xobject/fontable.pyi
Xlib-stubs/xobject/icccm.pyi
Xlib-stubs/xobject/resource.pyi
types_python_xlib-0.33.0.20250602.dist-info/licenses/LICENSE
types_python_xlib-0.33.0.20250602.dist-info/METADATA
types_python_xlib-0.33.0.20250602.dist-info/WHEEL
types_python_xlib-0.33.0.20250602.dist-info/top_level.txt
types_python_xlib-0.33.0.20250602.dist-info/RECORD
